LICENSE
README.md
setup.py
propelauth_py/__init__.py
propelauth_py/auth_fns.py
propelauth_py/errors.py
propelauth_py/jwt.py
propelauth_py/logging_config.py
propelauth_py/user.py
propelauth_py/validation.py
propelauth_py.egg-info/PKG-INFO
propelauth_py.egg-info/SOURCES.txt
propelauth_py.egg-info/dependency_links.txt
propelauth_py.egg-info/requires.txt
propelauth_py.egg-info/top_level.txt
propelauth_py/api/__init__.py
propelauth_py/api/access_token.py
propelauth_py/api/end_user_api_keys.py
propelauth_py/api/magic_link.py
propelauth_py/api/migrate_user.py
propelauth_py/api/org.py
propelauth_py/api/token_verification_metadata.py
propelauth_py/api/user.py
propelauth_py/api/step_up_mfa/__init__.py
propelauth_py/api/step_up_mfa/verify_grant.py
propelauth_py/api/step_up_mfa/verify_totp_challenge.py
propelauth_py/types/__init__.py
propelauth_py/types/custom_role_mappings.py
propelauth_py/types/end_user_api_keys.py
propelauth_py/types/login_method.py
propelauth_py/types/saml_types.py
propelauth_py/types/step_up_mfa.py
propelauth_py/types/user.py