Metadata-Version: 2.1
Name: propelauth-py
Version: 4.2.8
Summary: A python authentication library
Home-page: https://github.com/propelauth/propelauth-py
Author: PropelAuth
Author-email: support@propelauth.com
License: MIT
Platform: UNKNOWN
License-File: LICENSE
